jupytemplate
tests
