Metadata-Version: 2.1
Name: jupytemplate
Version: 0.2.3
Summary: Jupyter extension to support templates
Home-page: https://github.com/xtreamsrl/jupytemplate
Author: Emanuele Fabbiani @ xtream
Author-email: donlelef@gmail.com
License: MIT licence
Download-URL: https://github.com/xtreamsrl/jupytemplate/archive/v0.2.3.tar.gz
Platform: UNKNOWN
Classifier: Development Status :: 3 - Alpha
Classifier: Intended Audience :: End Users/Desktop
Classifier: Intended Audience :: Science/Research
Classifier: License :: OSI Approved :: MIT License
Classifier: Natural Language :: English
Classifier: Operating System :: OS Independent
Classifier: Programming Language :: JavaScript
Classifier: Programming Language :: Python :: 3.8
Classifier: Programming Language :: Python :: 3.7
Classifier: Programming Language :: Python :: 3.6
Classifier: Topic :: Utilities
